{
    "name": "Pay",
    "alias": "pay",
    "title": "pay::pay.title",
    "description": "pay::pay.description",
    "keywords": [],
    "version": "1.0.0",
    "active": 1,
    "installed": 1,
    "order": 10,
    "author": "allen qu",
    "email": "318566528@qq.com",
    "homepage": "http:\/\/www.zotop.com",
    "providers": [
        "Modules\\Pay\\Providers\\PayServiceProvider",
        "Modules\\Pay\\Providers\\RouteServiceProvider"
    ],
    "aliases": [],
    "files": [
        "start.php"
    ]
}